azure/synapse/managedprivateendpoints/__init__.py
azure/synapse/managedprivateendpoints/_configuration.py
azure/synapse/managedprivateendpoints/_managed_private_endpoints_client.py
azure/synapse/managedprivateendpoints/_version.py
azure/synapse/managedprivateendpoints/aio/__init__.py
azure/synapse/managedprivateendpoints/aio/_configuration.py
azure/synapse/managedprivateendpoints/aio/_managed_private_endpoints_client.py
azure/synapse/managedprivateendpoints/aio/operations/__init__.py
azure/synapse/managedprivateendpoints/aio/operations/_managed_private_endpoints_operations.py
azure/synapse/managedprivateendpoints/models/__init__.py
azure/synapse/managedprivateendpoints/models/_models.py
azure/synapse/managedprivateendpoints/models/_models_py3.py
azure/synapse/managedprivateendpoints/operations/__init__.py
azure/synapse/managedprivateendpoints/operations/_managed_private_endpoints_operations.py
azure_synapse_managedprivateendpoints-0.3.0.dist-info/METADATA
azure_synapse_managedprivateendpoints-0.3.0.dist-info/WHEEL
azure_synapse_managedprivateendpoints-0.3.0.dist-info/top_level.txt
azure_synapse_managedprivateendpoints-0.3.0.dist-info/RECORD
